{
  "hash": "c03adb8e",
  "configHash": "f912789c",
  "lockfileHash": "2a146bc3",
  "browserHash": "1c0e4b39",
  "optimized": {
    "react/jsx-dev-runtime": {
      "src": "../../node_modules/react/jsx-dev-runtime.js",
      "file": "react_jsx-dev-runtime.js",
      "fileHash": "8fd7cc06",
      "needsInterop": true
    },
    "react-dom/client": {
      "src": "../../node_modules/react-dom/client.js",
      "file": "react-dom_client.js",
      "fileHash": "206b0975",
      "needsInterop": true
    },
    "react": {
      "src": "../../node_modules/react/index.js",
      "file": "react.js",
      "fileHash": "d7407692",
      "needsInterop": true
    },
    "classnames": {
      "src": "../../node_modules/classnames/index.js",
      "file": "classnames.js",
      "fileHash": "a4854e52",
      "needsInterop": true
    },
    "react-dom": {
      "src": "../../node_modules/react-dom/index.js",
      "file": "react-dom.js",
      "fileHash": "c5b1aefc",
      "needsInterop": true
    }
  },
  "chunks": {
    "chunk-GQ53NV7R": {
      "file": "chunk-GQ53NV7R.js"
    },
    "chunk-I7K6YDV4": {
      "file": "chunk-I7K6YDV4.js"
    },
    "chunk-BUSYA2B4": {
      "file": "chunk-BUSYA2B4.js"
    }
  }
}